git_autoshare/__init__.py
git_autoshare/clone.py
git_autoshare/core.py
git_autoshare/giturlparse.py
git_autoshare/prefetch.py
git_autoshare/submodule.py
git_autoshare-1.0.0b6.dist-info/LICENSE.md
git_autoshare-1.0.0b6.dist-info/METADATA
git_autoshare-1.0.0b6.dist-info/WHEEL
git_autoshare-1.0.0b6.dist-info/entry_points.txt
git_autoshare-1.0.0b6.dist-info/top_level.txt
git_autoshare-1.0.0b6.dist-info/RECORD
