Metadata-Version: 2.1
Name: git-autoshare
Version: 1.0.0b6
Summary: A git clone wrapper that automatically uses --reference to save time and space.
Home-page: http://github.com/acsone/git-autoshare
Author: ACSONE SA/NV
Author-email: info@acsone.eu
License: GPLv3
Platform: UNKNOWN
Classifier: Development Status :: 3 - Alpha
Classifier: Intended Audience :: Developers
Classifier: License :: OSI Approved :: GNU General Public License v3 (GPLv3)
Classifier: Programming Language :: Python
Requires-Python: >=3.6
License-File: LICENSE.md
Requires-Dist: appdirs
Requires-Dist: click
Requires-Dist: pyyaml
